cot_forge/__init__.py
cot_forge/llm/__init__.py
cot_forge/llm/anthropic.py
cot_forge/llm/gemini.py
cot_forge/llm/groq.py
cot_forge/llm/hugging_face.py
cot_forge/llm/llm_provider.py
cot_forge/llm/lm_studio.py
cot_forge/llm/openai.py
cot_forge/llm/openrouter.py
cot_forge/persistence/__init__.py
cot_forge/persistence/persistence_manager.py
cot_forge/post_processing/__init__.py
cot_forge/post_processing/prompts.py
cot_forge/post_processing/reasoning_processor.py
cot_forge/pre_processing/claude.md
cot_forge/pre_processing/plan.md
cot_forge/reasoning/__init__.py
cot_forge/reasoning/cot_builder.py
cot_forge/reasoning/scorers/__init__.py
cot_forge/reasoning/scorers/base.py
cot_forge/reasoning/scorers/llm_scorers.py
cot_forge/reasoning/scorers/prompts.py
cot_forge/reasoning/search/__init__.py
cot_forge/reasoning/search/beam_search.py
cot_forge/reasoning/search/naive_linear_search.py
cot_forge/reasoning/search/search_algorithm.py
cot_forge/reasoning/strategies/__init__.py
cot_forge/reasoning/strategies/prompts.py
cot_forge/reasoning/strategies/strategies.py
cot_forge/reasoning/strategies/strategy_selector.py
cot_forge/reasoning/types.py
cot_forge/reasoning/verifiers/__init__.py
cot_forge/reasoning/verifiers/base.py
cot_forge/reasoning/verifiers/llm_verifiers.py
cot_forge/reasoning/verifiers/prompts.py
cot_forge/reasoning/verifiers/rule_verifiers.py
cot_forge/utils/__init__.py
cot_forge/utils/parsing.py
cot_forge/utils/search_utils.py
cot_forge-0.1.0.dist-info/LICENSE
cot_forge-0.1.0.dist-info/METADATA
cot_forge-0.1.0.dist-info/WHEEL
cot_forge-0.1.0.dist-info/RECORD
