Metadata-Version: 2.3
Name: cot-forge
Version: 0.1.0
Summary: A package for generation of chain-of-thought datasets.
License: MIT
Author: Matthew Samach
Author-email: msamach94@gmail.com
Requires-Python: >=3.10
Classifier: Programming Language :: Python :: 3
Requires-Dist: anthropic (>=0.49.0,<0.50.0)
Requires-Dist: google-api-core (>=2.24.1,<3.0.0)
Requires-Dist: google-genai (>=1.3.0,<2.0.0)
Requires-Dist: openai (>=1.68.2,<2.0.0)
Requires-Dist: tenacity (>=9.0.0,<10.0.0)
Requires-Dist: tiktoken (>=0.9.0,<0.10.0)
Requires-Dist: tqdm (>=4.67.1,<5.0.0)
Project-URL: Homepage, https://github.com/MattSamach/cot-forge
Project-URL: Issues, https://github.com/MattSamach/cot-forge/issues
